setup.py
umPlot.egg-info/PKG-INFO
umPlot.egg-info/SOURCES.txt
umPlot.egg-info/dependency_links.txt
umPlot.egg-info/requires.txt
umPlot.egg-info/top_level.txt
umplots/__init__.py
umplots/localTest.py
umplots/plotUtils.py