Metadata-Version: 1.0
Name: umPlot
Version: 0.0.1
Summary: with matplotlib and basemap plot data
Home-page: https://github.com/XiaoXiaowukong/umplot
Author: neo
Author-email: james_neo@163.com
License: MIT Licence
Keywords: pip,umPlot,plot
Platform: any
